otzovik_com/__init__.py
otzovik_com/otzovik_com.py
otzovik_com-0.1.7.dist-info/LICENSE
otzovik_com-0.1.7.dist-info/METADATA
otzovik_com-0.1.7.dist-info/WHEEL
otzovik_com-0.1.7.dist-info/top_level.txt
otzovik_com-0.1.7.dist-info/RECORD
